mx/__init__.py
mx/cli.py
mx/git.py
mx/logger.py
mx/tmux.py
mx/workspace.py
rafi.mx-0.2.11.dist-info/DESCRIPTION.rst
rafi.mx-0.2.11.dist-info/entry_points.txt
rafi.mx-0.2.11.dist-info/METADATA
rafi.mx-0.2.11.dist-info/metadata.json
rafi.mx-0.2.11.dist-info/RECORD
rafi.mx-0.2.11.dist-info/top_level.txt
rafi.mx-0.2.11.dist-info/WHEEL
