Metadata-Version: 2.0
Name: rafi.mx
Version: 0.2.11
Summary: Workspace/project-oriented tmux/git personal assistant.
Home-page: http://github.com/rafi/mx
Author: Rafael Bodill
Author-email: justrafi@gmail
License: MIT
Keywords: tmux git workspace project assistant
Platform: any
Classifier: Development Status :: 3 - Alpha
Classifier: License :: OSI Approved :: MIT License
Classifier: Environment :: Console
Classifier: Intended Audience :: Developers
Classifier: Intended Audience :: Customer Service
Classifier: Intended Audience :: System Administrators
Classifier: Operating System :: Microsoft
Classifier: Operating System :: MacOS :: MacOS X
Classifier: Operating System :: Unix
Classifier: Operating System :: POSIX
Classifier: Programming Language :: Python
Classifier: Programming Language :: Python :: 2.7
Classifier: Programming Language :: Python :: 3
Classifier: Programming Language :: Python :: 3.3
Classifier: Programming Language :: Python :: 3.4
Classifier: Programming Language :: Python :: 3.5
Classifier: Topic :: Software Development
Classifier: Topic :: Software Development :: Build Tools
Classifier: Topic :: Software Development :: Debuggers
Classifier: Topic :: Software Development :: Libraries
Classifier: Topic :: Software Development :: Libraries :: Python Modules
Classifier: Topic :: System :: Software Distribution
Classifier: Topic :: System :: Systems Administration
Classifier: Topic :: Utilities
Requires-Dist: PyYAML
